{"stats":{"minecraft:custom":{"minecraft:open_chest":1,"minecraft:time_since_rest":14885,"minecraft:play_time":40123,"minecraft:crouch_one_cm":3278,"minecraft:sprint_one_cm":71147,"minecraft:damage_taken":1265,"minecraft:deaths":4,"minecraft:walk_one_cm":35012,"minecraft:bell_ring":1,"minecraft:sneak_time":1355,"minecraft:walk_under_water_one_cm":1011,"minecraft:drop":3,"minecraft:jump":586,"minecraft:damage_dealt":6,"minecraft:leave_game":4,"minecraft:time_since_death":20053,"minecraft:walk_on_water_one_cm":1327,"minecraft:sleep_in_bed":1,"minecraft:total_world_time":40123,"minecraft:talked_to_villager":2,"minecraft:fall_one_cm":28320,"minecraft:fly_one_cm":88293},"minecraft:killed_by":{"minecraft:player":1},"minecraft:used":{"minecraft:dirt":7,"minecraft:egg":1},"minecraft:picked_up":{"minecraft:cooked_mutton":4,"minecraft:oak_log":2,"minecraft:dirt":8,"minecraft:egg":2},"minecraft:crafted":{"minecraft:oak_planks":8,"minecraft:crafting_table":1,"minecraft:stick":4},"minecraft:dropped":{"minecraft:dirt":1,"minecraft:cooked_mutton":2},"minecraft:mined":{"minecraft:oak_log":2,"minecraft:grass":4,"minecraft:grass_block":4,"minecraft:dirt":3,"minecraft:tall_grass":1,"minecraft:powder_snow":93,"minecraft:oak_leaves":1}},"DataVersion":3337}