{"stats":{"minecraft:used":{"minecraft:stone_pickaxe":49,"minecraft:stone_shovel":636,"minecraft:oak_planks":15,"minecraft:wooden_pickaxe":8,"minecraft:dirt":127,"minecraft:stone_axe":255,"minecraft:crafting_table":2,"minecraft:furnace":1,"minecraft:white_bed":1,"minecraft:cooked_beef":7},"minecraft:killed":{"minecraft:sheep":3,"minecraft:skeleton":2,"minecraft:zombie":4,"minecraft:pig":1,"minecraft:creeper":1,"minecraft:cow":2},"minecraft:custom":{"minecraft:time_since_rest":2580,"minecraft:interact_with_furnace":9,"minecraft:sprint_one_cm":94907,"minecraft:damage_taken":1140,"minecraft:walk_one_cm":219830,"minecraft:mob_kills":13,"minecraft:drop":1,"minecraft:damage_dealt":1894,"minecraft:swim_one_cm":15040,"minecraft:interact_with_crafting_table":11,"minecraft:fly_one_cm":122399,"minecraft:open_chest":3,"minecraft:play_time":64972,"minecraft:crouch_one_cm":14545,"minecraft:sneak_time":6268,"minecraft:deaths":2,"minecraft:walk_under_water_one_cm":8860,"minecraft:jump":818,"minecraft:leave_game":1,"minecraft:time_since_death":2551,"minecraft:walk_on_water_one_cm":6913,"minecraft:sleep_in_bed":3,"minecraft:total_world_time":64972,"minecraft:fall_one_cm":27056},"minecraft:mined":{"minecraft:birch_log":40,"minecraft:birch_leaves":3,"minecraft:crafting_table":1,"minecraft:grass":44,"minecraft:grass_block":547,"minecraft:coal_ore":12,"minecraft:oak_log":141,"minecraft:dirt":94,"minecraft:tall_grass":4,"minecraft:stone":41,"minecraft:oak_planks":2,"minecraft:oak_leaves":89},"minecraft:dropped":{"minecraft:oak_boat":1},"minecraft:picked_up":{"minecraft:birch_log":80,"minecraft:crafting_table":1,"minecraft:stick":44,"minecraft:cooked_beef":9,"minecraft:oak_door":2,"minecraft:leather":4,"minecraft:wooden_pickaxe":1,"minecraft:porkchop":10,"minecraft:oak_log":262,"minecraft:gunpowder":4,"minecraft:dirt":1249,"minecraft:bone":8,"minecraft:arrow":4,"minecraft:stone_shovel":4,"minecraft:rotten_flesh":10,"minecraft:apple":22,"minecraft:stone_axe":1,"minecraft:wheat_seeds":10,"minecraft:beef":7,"minecraft:stone_pickaxe":1,"minecraft:oak_sapling":78,"minecraft:birch_sapling":9,"minecraft:mutton":10,"minecraft:oak_planks":39,"minecraft:coal":21,"minecraft:white_wool":3,"minecraft:cobblestone":62},"minecraft:crafted":{"minecraft:cooked_beef":10,"minecraft:oak_boat":1,"minecraft:oak_planks":72,"minecraft:stone_shovel":7,"minecraft:crafting_table":1,"minecraft:stick":8,"minecraft:wooden_pickaxe":1,"minecraft:stone_pickaxe":1,"minecraft:furnace":1,"minecraft:white_bed":1,"minecraft:stone_axe":3},"minecraft:broken":{"minecraft:stone_shovel":4,"minecraft:stone_axe":2}},"DataVersion":3337}